setup.cfg
setup.py
cc_db/__init__.py
cc_db/cargocast_forecast_main.py
cc_db/engines.py
cc_db/session_handler.py
cc_db.egg-info/PKG-INFO
cc_db.egg-info/SOURCES.txt
cc_db.egg-info/dependency_links.txt
cc_db.egg-info/not-zip-safe
cc_db.egg-info/top_level.txt
cc_db/cargoline/__init__.py
cc_db/cargoline/partner.py
cc_db/company/__init__.py
cc_db/company/company.py
cc_db/forecast_model/__init__.py
cc_db/forecast_model/forecast.py
cc_db/forecast_model/forecastunit.py
cc_db/forecast_model/model.py
cc_db/forecast_model/observation.py
cc_db/forecast_model/timeindex.py
cc_db/forecast_model/weight.py