Metadata-Version: 1.0
Name: cc-db
Version: 1.83
Summary: CargoCast database interface
Home-page: UNKNOWN
Author: UNKNOWN
Author-email: pascal.dietirch@cargocast.com
License: UNKNOWN
Platform: UNKNOWN
